ipyloglite/__init__.py
ipyloglite-0.1.2.dist-info/LICENSE-APACHE
ipyloglite-0.1.2.dist-info/LICENSE-MIT
ipyloglite-0.1.2.dist-info/METADATA
ipyloglite-0.1.2.dist-info/WHEEL
ipyloglite-0.1.2.dist-info/top_level.txt
ipyloglite-0.1.2.dist-info/RECORD
