Metadata-Version: 2.1
Name: ipyloglite
Version: 0.1.2
Summary: Forward console.log and friends to cell outputs in JupyterLite.
Author-email: Juniper Tyree <juniper.tyree@helsinki.fi>
Maintainer-email: Juniper Tyree <juniper.tyree@helsinki.fi>
License:                                  Apache License
Requires-Python: >=3.7
Provides-Extra: dev
License-File: LICENSE-APACHE
License-File: LICENSE-MIT
